stylize/__init__.py
stylize/__main__.py
stylize/clang_formatter.py
stylize/formatter.py
stylize/util.py
stylize/yapf_formatter.py
stylize-0.3.2.dist-info/DESCRIPTION.rst
stylize-0.3.2.dist-info/METADATA
stylize-0.3.2.dist-info/RECORD
stylize-0.3.2.dist-info/WHEEL
stylize-0.3.2.dist-info/entry_points.txt
stylize-0.3.2.dist-info/metadata.json
stylize-0.3.2.dist-info/top_level.txt
