Metadata-Version: 2.0
Name: stylize
Version: 0.3.2
Summary: A tool for quickly formatting and checkstyling C/C++ and Python code
Home-page: https://github.com/justbuchanan/stylize
Author: Justin Buchanan
Author-email: justbuchanan@gmail.com
License: Apache License, Version 2.0
Platform: UNKNOWN
Classifier: Environment :: Console
Classifier: Intended Audience :: Developers
Classifier: Programming Language :: Python :: 3
Classifier: Programming Language :: Python :: 3.4
Classifier: Topic :: Software Development :: Quality Assurance
Requires-Dist: yapf
